LICENSE.md
MANIFEST.in
README.md
setup.cfg
setup.py
abfallwirtschaftfulda/__init__.py
abfallwirtschaftfulda/__version__.py
abfallwirtschaftfulda/abfallwirtschaftfulda.py
abfallwirtschaftfulda/const.py
abfallwirtschaftfulda/exceptions.py
abfallwirtschaftfulda.egg-info/PKG-INFO
abfallwirtschaftfulda.egg-info/SOURCES.txt
abfallwirtschaftfulda.egg-info/dependency_links.txt
abfallwirtschaftfulda.egg-info/not-zip-safe
abfallwirtschaftfulda.egg-info/requires.txt
abfallwirtschaftfulda.egg-info/top_level.txt