Metadata-Version: 2.1
Name: abfallwirtschaftfulda
Version: 0.1.1
Summary: Asynchronous Python client for Abfallwirtschaft Fulda.
Home-page: https://gitlab.com/stbkde/python-abfallwirtschaftfulda
Author: Stephan Beier
Author-email: stbkde@gmail.com
License: MIT license
Keywords: abfallwirtschaft fulda,abfallkalender,abfall,garbage calendar,garbage collection,api,async,client
Platform: UNKNOWN
Classifier: Development Status :: 4 - Beta
Classifier: Framework :: AsyncIO
Classifier: Intended Audience :: Developers
Classifier: License :: OSI Approved :: MIT License
Classifier: Natural Language :: English
Classifier: Programming Language :: Python :: 3.5
Classifier: Programming Language :: Python :: 3.6
Classifier: Programming Language :: Python :: 3.7
Classifier: Programming Language :: Python :: 3
Classifier: Topic :: Software Development :: Libraries :: Python Modules
